panel_xml/__init__.py
panel_xml/_xml.py
panel_xml/py.typed
panel_xml-0.1.4.dist-info/METADATA
panel_xml-0.1.4.dist-info/WHEEL
panel_xml-0.1.4.dist-info/RECORD
