Metadata-Version: 2.3
Name: panel-xml
Version: 0.1.4
Summary: A project providing a XML Pane for use with HoloViz Panel.
Author-email: Marc Skov Madsen <masma@gmail.com>
Requires-Python: >=3.9
Requires-Dist: panel>=1.5.2
Provides-Extra: dev
Requires-Dist: jedi-language-server; (sys_platform == 'linux') and extra == 'dev'
Requires-Dist: mypy; extra == 'dev'
Requires-Dist: panel; extra == 'dev'
Requires-Dist: pytest; extra == 'dev'
Requires-Dist: ruff; extra == 'dev'
Requires-Dist: watchfiles; extra == 'dev'
Provides-Extra: examples
Requires-Dist: panel-modal; extra == 'examples'
Requires-Dist: pygments; extra == 'examples'
Provides-Extra: tests
Requires-Dist: pytest; extra == 'tests'
